javaproperties/__init__.py
javaproperties/propclass.py
javaproperties/propfile.py
javaproperties/reading.py
javaproperties/util.py
javaproperties/writing.py
javaproperties/xmlprops.py
javaproperties-0.7.0.dist-info/LICENSE
javaproperties-0.7.0.dist-info/METADATA
javaproperties-0.7.0.dist-info/WHEEL
javaproperties-0.7.0.dist-info/top_level.txt
javaproperties-0.7.0.dist-info/RECORD
