Metadata-Version: 2.1
Name: javaproperties
Version: 0.7.0
Summary: Read & write Java .properties files
Home-page: https://github.com/jwodder/javaproperties
Author: John Thorvald Wodder II
Author-email: javaproperties@varonathe.org
License: MIT
Project-URL: Source Code, https://github.com/jwodder/javaproperties
Project-URL: Bug Tracker, https://github.com/jwodder/javaproperties/issues
Project-URL: Documentation, https://javaproperties.readthedocs.io
Project-URL: Say Thanks!, https://saythanks.io/to/jwodder
Keywords: java,properties,javaproperties,configfile,config,configuration
Platform: UNKNOWN
Classifier: Development Status :: 4 - Beta
Classifier: Programming Language :: Python :: 2
Classifier: Programming Language :: Python :: 2.7
Classifier: Programming Language :: Python :: 3
Classifier: Programming Language :: Python :: 3.4
Classifier: Programming Language :: Python :: 3.5
Classifier: Programming Language :: Python :: 3.6
Classifier: Programming Language :: Python :: 3.7
Classifier: Programming Language :: Python :: 3.8
Classifier: Programming Language :: Python :: Implementation :: CPython
Classifier: Programming Language :: Python :: Implementation :: PyPy
Classifier: License :: OSI Approved :: MIT License
Classifier: Intended Audience :: Developers
Classifier: Topic :: Software Development
Classifier: Topic :: Software Development :: Libraries :: Java Libraries
Classifier: Topic :: Utilities
Requires-Python: !=3.0.*,!=3.1.*,!=3.2.*,!=3.3.*,<4,>=2.7
Requires-Dist: six (~=1.4)
